{
    "MetaData": {
        "ContentFormatVersion": 4,
        "Id": "Base",
        "Name": "Base",
        "ResourcePath": "DATA/Characters/sruap_mage_vines/skins/base/Base.inibin"
    },
    "Values": {
        "MeshSkin": {
            "Animations": "Sruap_Mage_Vines.blnd",
            "ChampionSkinName": "SruapMageVines",
            "SelfIllumination": 0.7,
            "SimpleSkin": "Sruap_Mage_Vines.skn",
            "Skeleton": "Sruap_Mage_Vines.skl",
            "SkinScale": "1.0",
            "Texture": "Sruap_Mage_Vines_TX_CM.dds"
        }
    }
}