{
    "MetaData": {
        "ContentFormatVersion": 3,
        "Id": "VelkozW",
        "Name": "VelkozW",
        "ResourcePath": "DATA/Characters/Velkoz/Spells/VelkozW.inibin"
    },
    "Values": {
        "SpellData": {
            "AfterEffectName": "ChronoClockFast_tar.troy",
            "AlternateName": "",
            "AlwaysSnapFacing": "0",
            "AnimationLoopName": "",
            "AnimationName": "",
            "AnimationWinddownName": "",
            "ApplyAttackDamage": "0",
            "BelongsToAvatar": "0",
            "BounceRadius": "450.0000",
            "CanCastWhileDisabled": "0",
            "CannotBeSuppressed": "0",
            "CanOnlyCastWhileDead": "0",
            "CantCancelWhileChanneling": "0",
            "CantCancelWhileWindingUp": 1,
            "CantCastWhileRooted": "0",
            "CastConeAngle": "45.0000",
            "CastConeDistance": "100.0000",
            "CastFrame": 1.92,
            "CastRadius": "210.0000",
            "CastRadiusSecondary": 0,
            "CastRadiusSecondaryTexture": "",
            "CastRadiusTexture": "AOE.tga",
            "CastRange": "25000",
            "CastRangeDisplayOverride": "1050",
            "CastRangeUseBoundingBoxes": "0",
            "CastTargetAdditionalUnitsRadius": 0,
            "CastType": "0",
            "Coefficient": 0.25,
            "Coefficient2": 0.375,
            "Cooldown": 1.5,
            "DeathRecapPriority": 13,
            "DelayCastOffsetPercent": -0.5,
            "DelayTotalTimePercent": -0.5,
            "Description": "game_spell_description_VelkozW",
            "DisplayName": "game_spell_displayname_VelkozW",
            "DynamicExtended": "game_spell_levelup_VelkozW",
            "DynamicTooltip": "game_spell_tooltip_VelkozW",
            "Flags": 347148,
            "HaveAfterEffect": "0",
            "HaveHitBone": 1,
            "HaveHitEffect": "0",
            "HavePointEffect": "0",
            "HitBoneName": "C_BUFFBONE_GLB_HEAD_LOC",
            "HitEffectName": "rhyzebasicattack2_mis.troy",
            "InventoryIcon": "Velkoz_W.dds",
            "IsDisabledWhileDead": 1,
            "IsToggleSpell": "0",
            "LineDragLength": "0",
            "LineMissileBounces": "0",
            "LineMissileDelayDestroyAtEndSeconds": 0,
            "LineMissileEndsAtTargetPoint": "0",
            "LineMissileTargetHeightAugment": 0,
            "LineMissileTimePulseBetweenCollisionSpellHits": 0,
            "LineMissileTrackUnits": "0",
            "LineWidth": 87.5,
            "LockConeToPlayer": "0",
            "LookAtPolicy": "on",
            "LuaOnMissileUpdateDistanceInterval": 0,
            "MaxAmmo": 2,
            "MissileAccel": 0,
            "MissileBoneName": "R_hand",
            "MissileEffect": "DarkBinding_mis.troy",
            "MissileFixedTravelTime": 0,
            "MissileGravity": 0,
            "MissileMaxSpeed": "1200.0000",
            "MissileMinSpeed": "1200.0000",
            "MissilePerceptionBubbleRadius": 0,
            "MissilePerceptionBubbleRevealsStealth": "0",
            "MissileSpeed": "1200.0000",
            "MissileTargetHeightAugment": "100.0000",
            "OverrideCastTime": 0,
            "ParticleStartOffset": "0.0000 0.0000 0.0000",
            "PointEffectName": "",
            "SelectionPreference": "friend",
            "SpellRevealsChampion": 1,
            "StartCooldown": 0,
            "TargettingType": 6,
            "UseAnimatorFramerate": "0",
            "UseMinimapTargeting": "0",
            "Version": 1
        },
        "UNKNOWN_HASHES": {
            "1068464087": 25,
            "1090971346": 165,
            "1307804625": 0.25,
            "1469470033": 25,
            "1536257324": "0",
            "1608628182": 25,
            "1631135441": "100",
            "1770293590": 25,
            "1792800849": 135,
            "1829373218": "Instacast | PersistThroughDeath | AffectEnemies | AffectFriends | AffectNeutral | AffectHeroes | AlwaysSelf",
            "1931958998": 0.5,
            "1954466257": "110",
            "204969176": 25,
            "2171299536": 25,
            "227476435": "100",
            "2310457685": 25,
            "2332964944": "100",
            "237522587": "0",
            "2472123093": 25,
            "2494630352": 105,
            "2633788501": 0.5,
            "2656295760": "90",
            "278926620": "DefaultRangeIndicator.dds",
            "2795453909": 0.25,
            "3012287188": 25,
            "3034794447": "100",
            "3063333847": 18,
            "3063333848": 17,
            "3063333849": 16,
            "3063333850": 15,
            "3063333851": 14,
            "307233808": "0",
            "3171254284": "0",
            "3173952596": 25,
            "3196459855": 75,
            "3335618004": 0.5,
            "3358125263": "70",
            "3497283412": 0.25,
            "3658948820": 25,
            "3771724453": "50",
            "3771724454": 55,
            "3771724455": "60",
            "3771724456": 65,
            "3771724457": "70",
            "3875782099": 25,
            "3898289358": 45,
            "4037447507": 0.5,
            "4059954766": "50",
            "4199112915": 0.25,
            "444309714": 0.5,
            "466816973": "30",
            "536890465": "0",
            "57583389": "0",
            "605975122": 0.25,
            "65811027": 25,
            "767640530": 25,
            "906798679": 25,
            "929305938": "100",
            "944948707": "0"
        }
    }
}