{
    "MetaData": {
        "ContentFormatVersion": 3,
        "Id": "KatarinaR",
        "Name": "KatarinaR",
        "ResourcePath": "DATA/Spells/KatarinaR.inibin"
    },
    "Values": {
        "SpellData": {
            "AfterEffectName": "RapidFire_buf.troy",
            "AnimationLoopName": "Spell4",
            "AnimationName": "Spell4",
            "ApplyAttackDamage": "0",
            "BelongsToAvatar": "0",
            "BounceRadius": "450.0000",
            "CanCastWhileDisabled": "0",
            "CanOnlyCastWhileDead": "0",
            "CantCancelWhileChanneling": "0",
            "CantCancelWhileWindingUp": 1,
            "CastConeAngle": "45.0000",
            "CastConeDistance": "100.0000",
            "CastFrame": 5.4,
            "CastRadius": "325.0000",
            "CastRange": "550.0000",
            "CastRangeDisplayOverride": 0,
            "CastTargetAdditionalUnitsRadius": 0,
            "CastType": "0",
            "Coefficient": 2.5,
            "Coefficient2": 3.75,
            "DeathRecapPriority": "0",
            "DelayCastOffsetPercent": -0.5,
            "DelayTotalTimePercent": -0.5,
            "Description": "game_spell_description_KatarinaR",
            "DisplayName": "game_spell_displayname_KatarinaR",
            "DynamicExtended": "game_spell_levelup_KatarinaR",
            "DynamicTooltip": "game_spell_tooltip_KatarinaR",
            "Flags": 115712,
            "FloatVarsDecimals1": "0",
            "FloatVarsDecimals2": "0",
            "FloatVarsDecimals3": "0",
            "HaveAfterEffect": "0",
            "HaveHitBone": "0",
            "HaveHitEffect": "0",
            "HavePointEffect": "0",
            "HitBoneName": "",
            "HitEffectName": "AnnieBasicAttack_mis.troy",
            "InventoryIcon": "Katarina_DeathLotus.dds",
            "IsDisabledWhileDead": 1,
            "IsToggleSpell": "0",
            "LineMissileBounces": "0",
            "LineWidth": 0,
            "LocationTargettingWidth1": 0,
            "LockConeToPlayer": "0",
            "MissileBoneName": "weapon",
            "MissileEffect": "TristannaBasicAttack4_mis.troy",
            "MissileGravity": 0,
            "MissileSpeed": "1450.0000",
            "OverrideCastTime": 0.001,
            "ParticleStartOffset": "0.0000 0.0000 0.0000",
            "PointEffectName": "",
            "SelectionPreference": "foe",
            "Sound_VOEventCategory": "Emote",
            "StartCooldown": 0,
            "TargettingType": 4,
            "Version": 1
        },
        "UNKNOWN_HASHES": {
            "1090971346": 0,
            "1168646476": 0,
            "1631135441": 2.5,
            "1792800849": 0,
            "1829373218": "AffectEnemies | AffectNeutral | AffectMinions | AffectHeroes",
            "1832732728": "Level 3",
            "2257188466": "tristana_rapid_fire_cast.wav",
            "227476435": 0,
            "2332964944": 2.5,
            "2494630352": "3.0000",
            "2513139448": 0,
            "2513139449": 0,
            "2513139450": 0,
            "2513139451": 0,
            "2629301966": "90.0000",
            "2629301967": "60.0000",
            "2629301968": "45.0000",
            "2629301969": 0,
            "2629301970": 0,
            "278926620": "DefaultRangeIndicator.dds",
            "2893618454": "none.wav",
            "2972297017": "Level 4",
            "3034794447": 2.5,
            "305151565": 0,
            "3196459855": "3.0000",
            "3358125263": "75.0000",
            "3736623950": 0,
            "3771724453": 0,
            "3771724454": 0,
            "3771724455": 0,
            "3771724456": 0,
            "3771724457": 0,
            "3848571446": "Level 1",
            "3898289358": "3.0000",
            "402810463": 0,
            "402810464": 0,
            "402810465": 0,
            "402810466": 0,
            "402810467": 0,
            "4059954766": "55.0000",
            "4111861306": "Level 5",
            "466816973": "35.0000",
            "536890465": "0",
            "57583389": "0",
            "693168439": "Level 2",
            "929305938": 0
        }
    }
}