{
    "MetaData": {
        "ContentFormatVersion": 4,
        "Id": "RewindCOF",
        "Name": "RewindCOF",
        "ResourcePath": "DATA/Spells/RewindCOF.inibin"
    },
    "Values": {
        "SpellData": {
            "AfterEffectName": "ChronoRefresh_tar.troy",
            "AnimationLoopName": "",
            "AnimationName": "Spell4",
            "AnimationWinddownName": "",
            "ApplyAttackDamage": "0",
            "BelongsToAvatar": "0",
            "BounceRadius": "450.0000",
            "CantCancelWhileChanneling": "0",
            "CantCancelWhileWindingUp": 1,
            "CastConeAngle": "45.0000",
            "CastConeDistance": "100.0000",
            "CastFrame": 12.905,
            "CastRadius": "300.0000",
            "CastRange": "600.0000",
            "CastTargetAdditionalUnitsRadius": 0,
            "CastType": "0",
            "Coefficient": "1.0000",
            "Cooldown": 0,
            "Cooldown1": "36.0000",
            "Cooldown2": "30.0000",
            "Cooldown3": "24.0000",
            "Cooldown4": "18.0000",
            "Cooldown5": "12.0000",
            "DelayCastOffsetPercent": 0.0366,
            "DelayTotalTimePercent": -0.4875,
            "Description": "game_spell_description_Rewind",
            "DisplayName": "game_spell_displayname_Rewind",
            "DynamicExtended": "game_spell_levelup_Rewind",
            "DynamicTooltip": "game_spell_tooltip_Rewind",
            "Effect1Level0Amount": 0,
            "Effect1Level1Amount": "20.0000",
            "Effect1Level2Amount": "30.0000",
            "Effect1Level3Amount": "40.0000",
            "Effect1Level4Amount": "50.0000",
            "Effect1Level5Amount": "60.0000",
            "Effect2Level0Amount": 0,
            "Effect2Level1Amount": "5.0000",
            "Effect2Level2Amount": "5.0000",
            "Effect2Level3Amount": "5.0000",
            "Effect2Level4Amount": "5.0000",
            "Effect2Level5Amount": "5.0000",
            "Effect3Level0Amount": 0,
            "Effect3Level1Amount": 0,
            "Effect3Level2Amount": 0,
            "Effect3Level3Amount": 0,
            "Effect3Level4Amount": 0,
            "Effect3Level5Amount": 0,
            "Flags": 329732,
            "HaveAfterEffect": "0",
            "HaveHitBone": "0",
            "HaveHitEffect": "0",
            "HavePointEffect": "0",
            "HitBoneName": "head",
            "HitEffectName": "ChronoRefresh_tar.troy",
            "InventoryIcon": "Chronokeeper_Recall.dds",
            "IsDisabledWhileDead": 1,
            "IsToggleSpell": "0",
            "Level1Desc": "Level 1",
            "Level2Desc": "Level 2",
            "Level3Desc": "Level 3",
            "Level4Desc": "Level 4",
            "Level5Desc": "Level 5",
            "LineMissileBounces": "0",
            "LineWidth": 0,
            "ManaCost1": "50.0000",
            "ManaCost2": "50.0000",
            "ManaCost3": "50.0000",
            "ManaCost4": "50.0000",
            "ManaCost5": "50.0000",
            "MissileBoneName": "R_hand",
            "MissileEffect": "AnnieBasicAttack_mis.troy",
            "MissileSpeed": "20.0000",
            "PointEffectName": "",
            "SelectionPreference": "friend",
            "Sound_CastName": "Minotaur_Pulverize.wav",
            "Sound_HitName": "none.wav",
            "StartCooldown": 0,
            "SubjectToGlobalCooldown": "0",
            "TargettingType": "0",
            "TextFlags": "Instacast | AffectFriends | AffectHeroes | AlwaysSelf",
            "TriggersGlobalCooldown": "0",
            "Version": 1
        },
        "UNKNOWN_HASHES": {
            "3251122316": "50.0000"
        }
    }
}