{
    "MetaData": {
        "ContentFormatVersion": 4,
        "Id": "Braum",
        "Name": "Braum",
        "ResourcePath": "DATA/Characters/Braum/Braum.inibin"
    },
    "Values": {
        "Data": {
            "AbilityPowerIncPerLevel": "0",
            "AcquisitionRange": "600",
            "Armor": "20",
            "ArmorMaterial": "Flesh",
            "ArmorPerLevel": 4,
            "AttackDelayCastOffsetPercent": -0.07,
            "AttackDelayOffsetPercent": -0.03,
            "AttackRange": 125,
            "AttackSpeedPerLevel": 3.5,
            "BaseAbilityPower": "0",
            "BaseAttack_Probability": 1,
            "BaseCritChance": "0",
            "BaseDamage": 53,
            "BaseDodge": "0",
            "BaseFactorHPRegen": "0",
            "BaseFactorMPRegen": "0",
            "BaseHP": "430",
            "BaseMP": 235,
            "BaseStaticHPRegen": 1.30000007,
            "BaseStaticMPRegen": 1.1,
            "championId": 201,
            "ChasingAttackRangePercent": 0.8,
            "CritAttack_AttackDelayCastOffsetPercent": -0.07,
            "CritAttack_AttackDelayOffsetPercent": "-0.03",
            "CritDamageBonus": 2,
            "CritPerLevel": "0",
            "DamagePerLevel": 3.2,
            "Description": "game_character_description_Braum",
            "ExtraAttack1": "BraumBasicAttack2",
            "ExtraAttack1_Probability": "0",
            "ExtraAttack2": "BraumBasicAttack3",
            "ExtraAttack2_Probability": "0",
            "ExtraSpell1": "BraumQMissile",
            "ExtraSpell2": "",
            "ExtraSpell3": "BraumBasicAttackShieldOverride",
            "ExtraSpell4": "",
            "ExtraSpell5": "BraumRMissile",
            "ExtraSpell6": "BraumBasicAttackPassiveOverride",
            "ExtraSpell9": "BraumBasicAttackTower",
            "GameplayCollisionRadius": "80.0",
            "HPPerLevel": 87,
            "HPRegenPerLevel": 0.2,
            "IsMelee": "true",
            "LevelDodge": "0",
            "Lore1": "game_character_lore_Braum",
            "MaxLevels": "5 5 5 3",
            "MoveSpeed": 335,
            "MPPerLevel": 45,
            "MPRegenPerLevel": 0.16,
            "Name": "game_character_displayname_Braum",
            "Passive1Icon": "Braum_Passive.dds",
            "Passive1LuaName": "BraumMarkDamageTracker",
            "Passive1Name": "game_character_passiveName_Braum",
            "PassLev1Desc1": "game_character_passiveDescription_Braum",
            "PathfindingCollisionRadius": "50.0",
            "PlatformEnabled": "true",
            "PostAttackMoveDelay": 0,
            "SelectionHeight": 122,
            "SelectionRadius": "100",
            "Spell1": "BraumQ",
            "Spell2": "BraumW",
            "Spell3": "BraumE",
            "Spell4": "BraumRWrapper",
            "SpellBlock": "30",
            "SpellBlockPerLevel": 1.25,
            "SpellSupLevels1": "1 3 5 7 9 11",
            "SpellSupLevels2": "1 3 5 7 9 11",
            "SpellSupLevels3": "1 3 5 7 9 11",
            "SpellSupLevels4": "6 11 16",
            "Tips1": "game_character_tips_Braum",
            "Tips2": "game_character_opposing_tips_Braum",
            "WeaponMaterial": "OlafBasicAttack"
        },
        "DefaultAnimations": {
            "Animation1": "Idle_shield",
            "NumberOfAnimations": 1
        },
        "HealthBar": {
            "ParallaxOffset": "0",
            "XOffset": "0",
            "YOffset": -0.4
        },
        "IdleParticles": {
            "NumberOfParticles": 3,
            "Particle1": "Braum_Base_I_shield_Idle.troy Cstm_Buffbone_Shield_Gem",
            "Particle2": "Braum_Base_I_shield_left_eye.troy Cstm_Buffbone_L_Shield_Eye",
            "Particle3": "Braum_Base_I_shield_right_eye.troy Cstm_Buffbone_R_Shield_Eye"
        },
        "Info": {
            "IconCircle": "Braum_Circle.dds",
            "IconSquare": "Braum_Square.dds"
        },
        "UNKNOWN_HASHES": {
            "1040761625": 4,
            "105898023": 6,
            "2179197562": "false",
            "2441097661": "SUPPORT",
            "245402728": "Attack1.wav",
            "245402729": "Attack2.wav",
            "245402730": "Attack3.wav",
            "245402731": "Attack4.wav",
            "2500095475": "tank",
            "2786390348": 9,
            "4123230931": "Death.wav",
            "4146314945": "support",
            "767627316": 3,
            "923756730": "false"
        }
    }
}